82a9654e2dbb6f56a5e7__mypyc.cpython-311-x86_64-linux-gnu.so
tests/__init__.py
tests/test_main.py
rsv-1.5.3.dist-info/WHEEL
rsv-1.5.3.dist-info/RECORD
rsv-1.5.3.dist-info/top_level.txt
rsv-1.5.3.dist-info/METADATA
rsv-1.5.3.dist-info/licenses/LICENSE
rsv/encoder.cpython-311-x86_64-linux-gnu.so
rsv/__init__.cpython-311-x86_64-linux-gnu.so
rsv/decoder.cpython-311-x86_64-linux-gnu.so
rsv/rsv.cpython-311-x86_64-linux-gnu.so
rsv/decoder.py
rsv/__init__.py
rsv/rsv.py
rsv/encoder.py
