Metadata-Version: 2.4
Name: rsv
Version: 1.5.3
Summary: A module for reading and writing an RSV document file.
Home-page: https://github.com/romanin-rf/rsv
Author: Romanin
Author-email: Romanin <semina054@gmail.com>, Matthew Martin <matthewdeanmartin@gmail.com>
License: MIT
Keywords: rsv,csv,io,file,format,dump,load,read,write
Classifier: Development Status :: 5 - Production/Stable
Classifier: Operating System :: OS Independent
Classifier: Intended Audience :: Developers
Classifier: License :: OSI Approved :: MIT License
Classifier: Programming Language :: Python :: 3
Classifier: Programming Language :: Python :: 3.9
Classifier: Programming Language :: Python :: 3.10
Classifier: Programming Language :: Python :: 3.11
Classifier: Programming Language :: Python :: 3.12
Classifier: Programming Language :: Python :: 3.13
Classifier: Topic :: Software Development
Classifier: Typing :: Typed
Requires-Python: >=3.9
License-File: LICENSE
Dynamic: author
Dynamic: home-page
Dynamic: license-file
Dynamic: requires-python
